CHANGELOG.md
LICENSE.md
MANIFEST.in
README.md
pyproject.toml
setup.py
src/dbtease/__init__.py
src/dbtease/cli.py
src/dbtease/common.py
src/dbtease/config.ini
src/dbtease/config_context.py
src/dbtease/cron.py
src/dbtease/dbt.py
src/dbtease/git.py
src/dbtease/schedule.py
src/dbtease/schema.py
src/dbtease/shell.py
src/dbtease.egg-info/PKG-INFO
src/dbtease.egg-info/SOURCES.txt
src/dbtease.egg-info/dependency_links.txt
src/dbtease.egg-info/entry_points.txt
src/dbtease.egg-info/requires.txt
src/dbtease.egg-info/top_level.txt
src/dbtease/alerts/__init__.py
src/dbtease/alerts/base.py
src/dbtease/alerts/bundle.py
src/dbtease/alerts/logger.py
src/dbtease/alerts/slack.py
src/dbtease/filestores/__init__.py
src/dbtease/filestores/aws.py
src/dbtease/filestores/base.py
src/dbtease/filestores/local.py
src/dbtease/warehouses/__init__.py
src/dbtease/warehouses/base.py
src/dbtease/warehouses/snowflake.py
test/test_common.py
test/test_schedule.py