Metadata-Version: 2.1
Name: dbtease
Version: 0.0.1a3
Summary: CLI for deploying large dbt projects in pieces.
Home-page: https://github.com/tailsdotcom/dbtease
Author: Alan Cruickshank
Author-email: alan@tails.com
License: MIT License
Project-URL: Source, https://github.com/tailsdotcom/dbtease
Keywords: dbt
Platform: UNKNOWN
Classifier: Development Status :: 3 - Alpha
Classifier: Environment :: Console
Classifier: Intended Audience :: Developers
Classifier: License :: OSI Approved :: MIT License
Classifier: Operating System :: Unix
Classifier: Operating System :: POSIX
Classifier: Operating System :: Microsoft :: Windows
Classifier: Programming Language :: Python
Classifier: Programming Language :: Python :: 3
Classifier: Programming Language :: Python :: 3.6
Classifier: Programming Language :: Python :: 3.7
Classifier: Programming Language :: Python :: 3.8
Classifier: Programming Language :: Python :: 3.9
Classifier: Programming Language :: Python :: Implementation :: CPython
Classifier: Programming Language :: Python :: Implementation :: PyPy
Classifier: Topic :: Utilities
Requires-Python: >=3.6
